birdepy/__init__.py
birdepy/aug_expm.py
birdepy/aug_ilt.py
birdepy/aug_num.py
birdepy/em_Lange.py
birdepy/em_cg.py
birdepy/em_none.py
birdepy/em_qn1.py
birdepy/em_qn2.py
birdepy/gpu_functions.py
birdepy/interface_abc.py
birdepy/interface_aug.py
birdepy/interface_dnm.py
birdepy/interface_em.py
birdepy/interface_estimate.py
birdepy/interface_forecast.py
birdepy/interface_lse.py
birdepy/interface_probability.py
birdepy/probability_Erlang.py
birdepy/probability_da.py
birdepy/probability_expm.py
birdepy/probability_gwa.py
birdepy/probability_gwasa.py
birdepy/probability_ilt.py
birdepy/probability_oua.py
birdepy/probability_sim.py
birdepy/probability_uniform.py
birdepy/simulate.py
birdepy/squares_expm.py
birdepy/squares_fm.py
birdepy/squares_gwa.py
birdepy/utility.py
birdepy/utility_em.py
birdepy/utility_probability.py
birdepy/data_files/__init__.py
birdepy/data_files/iltcme.json
birdepy-1.0.0.dist-info/LICENSE
birdepy-1.0.0.dist-info/METADATA
birdepy-1.0.0.dist-info/WHEEL
birdepy-1.0.0.dist-info/entry_points.txt
birdepy-1.0.0.dist-info/top_level.txt
birdepy-1.0.0.dist-info/RECORD
