Metadata-Version: 2.1
Name: birdepy
Version: 1.0.0
Summary: Parameter estimation for birth-and-death processes
Home-page: https://birdepy.github.io
Author: Sophie Hautphenne and Brendan Patch
Author-email: birdepy@gmail.com
Project-URL: Bug Reports, https://github.com/birdepy/birdepy_project/issues
Project-URL: Source, https://github.com/birdepy/birdepy_project
Keywords: Markov chain,stochastic,population process
Classifier: Development Status :: 4 - Beta
Classifier: License :: OSI Approved :: GNU General Public License v3 (GPLv3)
Classifier: Programming Language :: Python :: 3.10
Classifier: Programming Language :: Python :: 3.11
Classifier: Programming Language :: Python :: 3 :: Only
Requires-Python: >=3.10
License-File: LICENSE
Requires-Dist: numpy>=1.17.0
Requires-Dist: mpmath>=1.2.0
Requires-Dist: scipy>=1.7.0
Requires-Dist: matplotlib>=3.4.2
Requires-Dist: gwr-inversion>=1.0.1
Requires-Dist: numba>=0.56.4
